_version.py
src/__init__.py
src/ctu_relational/ctu_relational_to_warehouse.py
src/google_takeout/__init__.py
src/google_takeout/extract_google_takeout_seed.py
src/google_takeout/google_takeout_seed_to_warehouse.py
src/google_takeout/models.py
src/google_takeout/parsers.py
src/google_takeout/sources.py
src/rss/models.py
src/rss/rss_feed_to_postgres.py
src/rss/sources.py
src/spotify/__init__.py
src/spotify/extract_spotify_seed.py
src/spotify/models.py
src/spotify/parsers.py
src/spotify/sources.py
src/spotify/spotify_seed_to_warehouse.py
src/utils/__init__.py
src/utils/storage.py
pypeline_functions-0.2.0.dist-info/METADATA
pypeline_functions-0.2.0.dist-info/WHEEL
pypeline_functions-0.2.0.dist-info/entry_points.txt
pypeline_functions-0.2.0.dist-info/licenses/LICENSE.txt
pypeline_functions-0.2.0.dist-info/RECORD
