Metadata-Version: 2.4
Name: pypeline-functions
Version: 0.2.0
Summary: A compiliation of data pipeline scripts in Python
Author-email: Miguel Habana <mighabana@gmail.com>
License: MIT
License-File: LICENSE.txt
Keywords: ELT,data pipelines,dlt,pypeline
Classifier: Development Status :: 2 - Pre-Alpha
Classifier: Intended Audience :: Developers
Classifier: License :: OSI Approved :: MIT License
Classifier: Programming Language :: Python :: 3
Classifier: Programming Language :: Python :: 3.11
Classifier: Programming Language :: Python :: 3.12
Classifier: Topic :: Software Development :: Libraries
Requires-Python: >=3.11
Requires-Dist: dlt>=1.0.0
Requires-Dist: fastparquet>=2024.5.0
Requires-Dist: feedparser>=6.0.11
Requires-Dist: google-auth>=2.34.0
Requires-Dist: google-cloud-bigquery-storage>=2.26.0
Requires-Dist: google-cloud-bigquery>=3.25.0
Requires-Dist: google-cloud-storage>=2.18.0
Requires-Dist: pandas>=2.2.0
Requires-Dist: psycopg2-binary>=2.9.10
Requires-Dist: pydantic>=2.9.0
Requires-Dist: python-magic>=0.4.27
Requires-Dist: stream-unzip>=0.0.90
Provides-Extra: dev
Requires-Dist: memray; extra == 'dev'
Requires-Dist: pre-commit; extra == 'dev'
Requires-Dist: ruff; extra == 'dev'
